{
  "url": "https://www.onlinegames.io/dragon-city/",
  "title": "Dragon City",
  "category": "/t/action/",
  "thumbnail": "https://www.onlinegames.io/media/posts/55/Dragon-City-Online.jpg",
  "thumbnailDetails": {
    "src": "https://www.onlinegames.io/media/posts/55/Dragon-City-Online.jpg",
    "srcset": "https://www.onlinegames.io/media/posts/55/responsive/Dragon-City-Online-xs.jpg 384w, https://www.onlinegames.io/media/posts/55/responsive/Dragon-City-Online-sm.jpg 600w, https://www.onlinegames.io/media/posts/55/responsive/Dragon-City-Online-md.jpg 768w, https://www.onlinegames.io/media/posts/55/responsive/Dragon-City-Online-lg.jpg 1200w",
    "alt": "Dragon City Online",
    "width": 256,
    "height": 256,
    "className": "is-loaded",
    "parentClass": "post__featured-image is-loaded"
  },
  "gameFrame": "https://unblocked-games.s3.amazonaws.com/games/dragon-city/index.html",
  "content": {
    "headings": [],
    "controls": [],
    "howToPlay": "",
    "tips": "",
    "developer": "",
    "similarGames": []
  },
  "fullContent": "Home› DragonDragon CityBy OnlineGames.ioMake Game Full Screen Dragon City is the game where you must protect your city from enemies. They will try to put you down by shooting but you are more powerful than them because you are shooting balls of fire. The dragon can also have other attack skills like fire breath and melee sweep. It can destroy the cars too.Test your power and fly with your dragon and dominate the city. There are 6 dragons you can choose from:• Volzid TheRedeemer • Irsho Eater of all (available to buy with 10000)• Osgu The Fierce (available to buy with 10000)• Taskath The Chosen (available at level 10)• Izorlu The Dark (available at level 20)• Askae The Insane (available at level 30)Dragon City Profile details:• Level • Xp • Kills • Money • Buy Gift Dont forget to collect the daily gift reward !Dragon City Display:• Kill feed (displayed on the top left)• Controls (displayed on the  left & right bottom )• City Map (displayed on the top right)Controls:WASD or arrow keys to move the dragonSpace to fly upLeft shift to sprintQ to jumpC to crouchR to dodgeShift + left mouse click for fire breathLeft mouse click for fireballRight mouse click for melee attackEsc, tab for pause menuThis article was updated on February 19, 20241 Player3DActionAdventureAnimalBattleCrazyDragonFantasyFlyingFree",
  "extractedAt": "2025-06-10T05:04:39.060Z",
  "localThumbnail": "Dragon City_1749531879060.jpg"
}